oracle_parquet_dumper/__init__.py
oracle_parquet_dumper/main.py
oracle_parquet_dumper-0.0.15.dist-info/METADATA
oracle_parquet_dumper-0.0.15.dist-info/WHEEL
oracle_parquet_dumper-0.0.15.dist-info/entry_points.txt
oracle_parquet_dumper-0.0.15.dist-info/top_level.txt
oracle_parquet_dumper-0.0.15.dist-info/RECORD
