Metadata-Version: 2.4
Name: oracle-parquet-dumper
Version: 0.0.15
Summary: A Python-based tool for dumping Oracle database table data to parquet files
Author-email: Philip Moore <philip@gizmodata.com>
Project-URL: Homepage, https://github.com/gizmodata/oracle-parquet-dumper
Keywords: oracle,parquet,dumper,data,export,apache,arrow
Classifier: License :: OSI Approved :: MIT License
Classifier: Programming Language :: Python
Classifier: Programming Language :: Python :: 3
Requires-Python: >=3.10
Requires-Dist: oracledb==3.0.*
Requires-Dist: pyarrow==19.0.*
Requires-Dist: click==8.1.*
Requires-Dist: codetiming==1.4.*
Requires-Dist: munch==4.0.*
Requires-Dist: python-dateutil==2.9.*
Requires-Dist: pytz==2025.*
Requires-Dist: python-dotenv==1.1.*
Provides-Extra: test
Requires-Dist: pytest; extra == "test"
Requires-Dist: pytest-snapshot; extra == "test"
Requires-Dist: pytest-mock; extra == "test"
Requires-Dist: filelock; extra == "test"
Requires-Dist: dask; extra == "test"
Requires-Dist: distributed; extra == "test"
Requires-Dist: pins[gcs]; extra == "test"
Requires-Dist: docker; extra == "test"
Provides-Extra: dev
Requires-Dist: bumpver; extra == "dev"
Requires-Dist: pip-tools; extra == "dev"
Requires-Dist: pytest; extra == "dev"
